<?xml version="1.0"?>
<!DOCTYPE hibernate-mapping PUBLIC "-//Hibernate/Hibernate Mapping DTD 3.0//EN"
"http://www.hibernate.org/dtd/hibernate-mapping-3.0.dtd">
<!-- Generated 30/03/2014 04:22:01 by Hibernate Tools 3.6.0 -->
<hibernate-mapping>
    <class name="com.au.pojo.Funcionario" table="funcionario" catalog="sistemapastelao">
        <id name="idFunc" type="java.lang.Integer">
            <column name="idFunc" />
            <generator class="identity" />
        </id>
        <property name="nomeFunc" type="string">
            <column name="nomeFunc" length="250" not-null="true" />
        </property>
        <property name="nascFunc" type="date">
            <column name="nascFunc" length="10" not-null="true" />
        </property>
        <property name="sexoFunc" type="string">
            <column name="sexoFunc" length="1" not-null="true" />
        </property>
        <property name="rgFunc" type="string">
            <column name="rgFunc" length="15" />
        </property>
        <property name="cpfFunc" type="string">
            <column name="cpfFunc" length="15" not-null="true" />
        </property>
        <property name="mailFunc" type="string">
            <column name="mailFunc" length="150" not-null="true" />
        </property>
        <property name="foneFunc" type="string">
            <column name="foneFunc" length="15" />
        </property>
        <property name="celFunc" type="string">
            <column name="celFunc" length="15" not-null="true" />
        </property>
        <property name="dtAdmFunc" type="date">
            <column name="dtAdmFunc" length="10" not-null="true" />
        </property>
        <property name="salFunc" type="double">
            <column name="salFunc" precision="22" scale="0" not-null="true" />
        </property>
        <property name="userFunc" type="string">
            <column name="userFunc" length="50" not-null="true" unique="true" />
        </property>
        <property name="passFunc" type="string">
            <column name="passFunc" length="64" not-null="true" />
        </property>
        <property name="nivelFunc" type="int">
            <column name="nivelFunc" not-null="true" />
        </property>
        <property name="estaAtivo" type="boolean">
            <column name="estaAtivo" not-null="true" />
        </property>
        <set name="caixas" table="caixa" inverse="true" lazy="true" fetch="select">
            <key>
                <column name="idFunc" not-null="true" />
            </key>
            <one-to-many class="com.au.pojo.Caixa" />
        </set>
    </class>
</hibernate-mapping>
